spotipy_tui
